libsrg_apps/DiskInfo.py
libsrg_apps/ReZFS.py
libsrg_apps/Stage0.py
libsrg_apps/__init__.py
libsrg_apps/ztool.py
libsrg_apps-1.1.2.dist-info/METADATA
libsrg_apps-1.1.2.dist-info/WHEEL
libsrg_apps-1.1.2.dist-info/RECORD
