Metadata-Version: 2.1
Name: libsrg-apps
Version: 1.1.2
Summary: This is a handful of applications migrated out of lilbsrg.
Author: Steve Goncalo
Author-email: steven@goncalo.us
Requires-Python: >=3.9,<4.0
Classifier: Development Status :: 4 - Beta
Classifier: Intended Audience :: System Administrators
Classifier: License :: OSI Approved :: MIT License
Classifier: Natural Language :: English
Classifier: Operating System :: POSIX :: Linux
Classifier: Programming Language :: Python :: 3
Classifier: Programming Language :: Python :: 3.9
Classifier: Programming Language :: Python :: 3.10
Classifier: Programming Language :: Python :: 3.11
Classifier: Programming Language :: Python :: 3.12
Classifier: Topic :: System :: Systems Administration
Classifier: Topic :: Utilities
Requires-Dist: libsrg (>=5.2.2,<6.0.0)
